{
  "reset_user_password" :{
    "message": "رمز عبور تان باز نشانی شده، لطفا رمز عبور تان را تغییر دهید",
    "message_english": "Your password has been reseted, please change your password",
    "url": "/profile#change-pass"
  },
  "add_new_contract" :{
    "message": "قرار داد جدید برای شما اضافه شد",
    "message_english": "New contract added for you",
    "url": "/profile#contract"
  },
  "leave_request_send" :{
    "message": "{} یک درخواست رخصتی فرستاده است",
    "message_english": "{} has a leave request",
    "url": "/leave_supervisor/{}"
  },
  "supervisor_leave_request_hr" :{
    "message": "{} یک درخواست رخصتی فرستاده است",
    "message_english": "{} has a leave request",
    "url": "/leave_hr/{}"
  },
  "supervisor_leave_request_employee" :{
    "message": "مسئول بخش درخواست رخصتی شما را {} است",
    "message_english": "Supervisor {} your leave request",
    "url": "/leave_request"
  },
  "hr_leave_request_employee" :{
    "message": "منابع بشری درخواست رخصتی شما را {} است",
    "message_english": "Human Resource {} your leave request",
    "url": "/leave_request"
  },
  "overtime_request_send" :{
    "message": "{} یک درخواست اضافه کاری فرستاده است",
    "message_english": "{} has a overtime request",
    "url": "/overtime_supervisor/{}"
  },
  "supervisor_overtime_request_hr" :{
    "message": "{} یک درخواست اضافه کاری فرستاده است",
    "message_english": "{} has a overtime request",
    "url": "/overtime_hr/{}"
  },
  "supervisor_overtime_request_employee" :{
    "message": "مسئول بخش درخواست اضافه کاری شما را {} است",
    "message_english": "Supervisor {} your overtime request",
    "url": "/overtime_request"
  },
  "hr_overtime_request_employee" :{
    "message": "منابع بشری درخواست اضافه کاری شما را {} است",
    "message_english": "Human Resource {} your overtime request",
    "url": "/overtime_request"
  },
  "loan_request_send_guarantor" :{
    "message": "{} درخواست قرضه کرده است و شما به عنوان ضامن هستید",
    "message_english": "{} has a loan request and you are as guarantor, ",
    "url": "/loan_guarantor/{}"
  },
  "guarantor_loan_request_employee" :{
    "message": "{} درخواست ضمانت برای  قرضه شما را {} است",
    "message_english": "{} has been {} your loan request",
    "url": "/loan_request"
  },
  "guarantor_loan_request_hr" :{
    "message": "{} یک درخواست قرضه فرستاده است",
    "message_english": "{} has a loan request",
    "url": "/loan_hr/{}"
  },
  "hr_loan_request_employee" :{
    "message": "منابع بشری درخواست قرضه شما را {} است",
    "message_english": "Human Resource has been {} your loan request",
    "url": "/loan_request"
  },
  "hr_loan_request_presidency" :{
    "message": "{} یک درخواست قرضه فرستاده است",
    "message_english": "{} has been send a loan request",
    "url": "/loan_presidency/{}"
  },
  "presidency_loan_request_employee" :{
    "message": "ریاست درخواست قرضه شما را {} است",
    "message_english": "Presidency has been {} your loan request",
    "url": "/loan_request"
  },
  "presidency_loan_request_finance" :{
    "message": "{} یک درخواست قرضه فرستاده است",
    "message_english": "{} has been send a loan request",
    "url": "/loan_finance/{}"
  },
  "finance_loan_request_employee" :{
    "message": "مدیریت مالی درخواست قرضه شما را {} است",
    "message_english": "Finance has been {} your loan request",
    "url": "/loan_request"
  },
  "finance_loan_request_presidency" :{
    "message": "مدیریت مالی درخواست قرضه {} را {} است",
    "message_english": "Finance has been {} loan request of {}",
    "url": "/loan_presidency/{}"
  }
}